ppppocr/__init__.py
ppppocr/downModel.py
ppppocr/ppppocr.py
ppppocr/ppppocr_test.py
ppppocr/rapid_ocr_api.py
ppppocr/test_demo.py
ppppocr/ch_ppocr_mobile_v2_cls/__init__.py
ppppocr/ch_ppocr_mobile_v2_cls/text_cls.py
ppppocr/ch_ppocr_mobile_v2_cls/utils.py
ppppocr/ch_ppocr_mobile_v2_det/__init__.py
ppppocr/ch_ppocr_mobile_v2_det/text_detect.py
ppppocr/ch_ppocr_mobile_v2_det/utils.py
ppppocr/ch_ppocr_mobile_v2_rec/__init__.py
ppppocr/ch_ppocr_mobile_v2_rec/text_recognize.py
ppppocr/ch_ppocr_mobile_v2_rec/utils.py
ppppocr/ch_ppocr_server_v2_det/__init__.py
ppppocr/ch_ppocr_server_v2_det/text_detect.py
ppppocr/ch_ppocr_server_v2_det/utils.py
ppppocr/ch_ppocr_server_v2_rec/__init__.py
ppppocr/ch_ppocr_server_v2_rec/text_recognize.py
ppppocr/ch_ppocr_server_v2_rec/utils.py
ppppocr/models/ch_PP-OCRv2_det_infer.onnx
ppppocr/models/ch_PP-OCRv2_rec_infer.onnx
ppppocr/models/ch_ppocr_mobile_v2.0_cls_infer.onnx
ppppocr/rec_dict/ar_dict.txt
ppppocr/rec_dict/arabic_dict.txt
ppppocr/rec_dict/be_dict.txt
ppppocr/rec_dict/bg_dict.txt
ppppocr/rec_dict/cyrillic_dict.txt
ppppocr/rec_dict/devanagari_dict.txt
ppppocr/rec_dict/en_dict.txt
ppppocr/rec_dict/fa_dict.txt
ppppocr/rec_dict/french_dict.txt
ppppocr/rec_dict/german_dict.txt
ppppocr/rec_dict/hi_dict.txt
ppppocr/rec_dict/it_dict.txt
ppppocr/rec_dict/japan_dict.txt
ppppocr/rec_dict/ka_dict.txt
ppppocr/rec_dict/korean_dict.txt
ppppocr/rec_dict/latin_dict.txt
ppppocr/rec_dict/mr_dict.txt
ppppocr/rec_dict/ne_dict.txt
ppppocr/rec_dict/oc_dict.txt
ppppocr/rec_dict/ppocr_keys_v1.txt
ppppocr/rec_dict/pu_dict.txt
ppppocr/rec_dict/rs_dict.txt
ppppocr/rec_dict/rsc_dict.txt
ppppocr/rec_dict/ru_dict.txt
ppppocr/rec_dict/ta_dict.txt
ppppocr/rec_dict/table_dict.txt
ppppocr/rec_dict/te_dict.txt
ppppocr/rec_dict/ug_dict.txt
ppppocr/rec_dict/uk_dict.txt
ppppocr/rec_dict/ur_dict.txt
ppppocr/rec_dict/xi_dict.txt
ppppocr-1.0.6.dist-info/METADATA
ppppocr-1.0.6.dist-info/WHEEL
ppppocr-1.0.6.dist-info/top_level.txt
ppppocr-1.0.6.dist-info/RECORD
