Metadata-Version: 2.1
Name: ppppocr
Version: 1.0.6
Summary: PPOCR
Home-page: https://github.com/duolabmeng6/ppppocr
Author: duolabmeng6
Author-email: 1715109585@qq.com
Keywords: ppocr paddleOCR ppppocr
Classifier: Programming Language :: Python :: 3
Classifier: License :: OSI Approved :: MIT License
Classifier: Operating System :: OS Independent
Requires-Dist: numpy
Requires-Dist: onnxruntime
Requires-Dist: Pillow
Requires-Dist: opencv-python
